emmetify/__init__.py
emmetify/config/__init__.py
emmetify/config/base_config.py
emmetify/config/html_config.py
emmetify/const.py
emmetify/converters/__init__.py
emmetify/converters/base_converter.py
emmetify/converters/html_converter.py
emmetify/data/__init__.py
emmetify/data/single_token_names.json
emmetify/data/single_token_words.json
emmetify/emmetifier.py
emmetify/nodes/__init__.py
emmetify/nodes/base_nodes.py
emmetify/nodes/html_nodes.py
emmetify/parsers/__init__.py
emmetify/parsers/base_parser.py
emmetify/parsers/html_parser.py
emmetify/types.py
emmetify/utils/__init__.py
emmetify/utils/tokens.py
emmetify/utils/xpath.py
emmetify-0.1.0.dist-info/LICENSE
emmetify-0.1.0.dist-info/METADATA
emmetify-0.1.0.dist-info/WHEEL
emmetify-0.1.0.dist-info/RECORD
