Metadata-Version: 2.3
Name: emmetify
Version: 0.1.0
Summary: Cut LLM costs and boost processing speed by transforming verbose HTML into efficient Emmet notation
License: Apache-2.0
Author: Mariusz Korzekwa
Author-email: mariusz@korzekwa.dev
Requires-Python: >=3.9
Classifier: Development Status :: 4 - Beta
Classifier: Intended Audience :: Developers
Classifier: License :: OSI Approved :: Apache Software License
Classifier: Programming Language :: Python :: 3
Classifier: Programming Language :: Python :: 3.9
Classifier: Programming Language :: Python :: 3.10
Classifier: Programming Language :: Python :: 3.11
Classifier: Programming Language :: Python :: 3.12
Classifier: Programming Language :: Python :: 3.13
Classifier: Topic :: Software Development :: Libraries :: Python Modules
Classifier: Topic :: Text Processing :: Markup :: HTML
Requires-Dist: beautifulsoup4 (>=4.12.3,<5.0.0)
Requires-Dist: lxml (>=5.3.0,<6.0.0)
Requires-Dist: pydantic (>=2.10.4,<3.0.0)
Project-URL: Repository, https://github.com/emmetify/emmetify-py
